{
    "Ar36": {
        "error": 0.00017204272903333055, 
        "fit": "previous", 
        "references": [
            {
                "exclude": false, 
                "record_id": "bc-02-J-907"
            }
        ], 
        "value": 0.003657723540998847
    }, 
    "Ar37": {
        "error": 0.0053214755473847165, 
        "fit": "previous", 
        "references": [
            {
                "exclude": false, 
                "record_id": "bc-02-J-907"
            }
        ], 
        "value": 0.04595608787435615
    }, 
    "Ar38": {
        "error": 0.002181141873031473, 
        "fit": "previous", 
        "references": [
            {
                "exclude": false, 
                "record_id": "bc-02-J-907"
            }
        ], 
        "value": 0.0026695345527808292
    }, 
    "Ar39": {
        "error": 0.009580157495925655, 
        "fit": "previous", 
        "references": [
            {
                "exclude": false, 
                "record_id": "bc-02-J-907"
            }
        ], 
        "value": 0.023011145728063107
    }, 
    "Ar40": {
        "error": 0.007505625823360266, 
        "fit": "previous", 
        "references": [
            {
                "exclude": false, 
                "record_id": "bc-02-J-907"
            }
        ], 
        "value": 0.32036375378043297
    }, 
    "Ar41": {
        "error": 0.0038088792681720243, 
        "fit": "previous", 
        "references": [
            {
                "exclude": false, 
                "record_id": "bc-02-J-907"
            }
        ], 
        "value": 0.016251504774124376
    }
}