{
    "AX": {
        "error": 0.004764976641618605, 
        "filter_outliers_dict": {
            "filter_outliers": true, 
            "iterations": 1, 
            "std_devs": 2
        }, 
        "fit": "average", 
        "value": 0.15465813573059178
    }, 
    "CDD": {
        "error": 4.742000182355931e-06, 
        "filter_outliers_dict": {
            "filter_outliers": true, 
            "iterations": 1, 
            "std_devs": 10
        }, 
        "fit": "average", 
        "value": 2.1015556528924884e-05
    }, 
    "H1": {
        "error": 0.0036306701522932456, 
        "filter_outliers_dict": {
            "filter_outliers": true, 
            "iterations": 1, 
            "std_devs": 2
        }, 
        "fit": "average", 
        "value": 0.08315474769926656
    }, 
    "H2": {
        "error": 0.003072624121616293, 
        "filter_outliers_dict": {
            "filter_outliers": true, 
            "iterations": 1, 
            "std_devs": 2
        }, 
        "fit": "average", 
        "value": -0.09167020106159224
    }, 
    "L1": {
        "error": 0.0018020645690014518, 
        "filter_outliers_dict": {
            "filter_outliers": true, 
            "iterations": 1, 
            "std_devs": 2
        }, 
        "fit": "average", 
        "value": -0.02582906388593695
    }, 
    "L2": {
        "error": 0.004132352636530229, 
        "filter_outliers_dict": {
            "filter_outliers": true, 
            "iterations": 1, 
            "std_devs": 2
        }, 
        "fit": "average", 
        "value": -0.015569699257713477
    }
}