{
    "Ar36": {
        "error": 0.00025412175365460465, 
        "filter_outliers_dict": {
            "filter_outliers": true, 
            "iterations": 1, 
            "std_devs": 2
        }, 
        "fit": "Parabolic", 
        "value": 0.012488167098216891
    }, 
    "Ar37": {
        "error": 0.00483463393284229, 
        "filter_outliers_dict": {
            "filter_outliers": true, 
            "iterations": 1, 
            "std_devs": 2
        }, 
        "fit": "linear", 
        "value": 0.03101450736394631
    }, 
    "Ar38": {
        "error": 0.00221781973026639, 
        "filter_outliers_dict": {
            "filter_outliers": true, 
            "iterations": 1, 
            "std_devs": 2
        }, 
        "fit": "linear", 
        "value": -0.02315229033022144
    }, 
    "Ar39": {
        "error": 0.009303581031715356, 
        "filter_outliers_dict": {
            "filter_outliers": true, 
            "iterations": 1, 
            "std_devs": 2
        }, 
        "fit": "Parabolic", 
        "value": -0.007976188310857345
    }, 
    "Ar40": {
        "error": 0.008250784962161889, 
        "filter_outliers_dict": {
            "filter_outliers": true, 
            "iterations": 1, 
            "std_devs": 2
        }, 
        "fit": "Parabolic", 
        "value": 2.9043449002416506
    }, 
    "Ar41": {
        "error": 0.003472220991931709, 
        "filter_outliers_dict": {
            "filter_outliers": true, 
            "iterations": 1, 
            "std_devs": 2
        }, 
        "fit": "linear", 
        "value": -0.08660582949273328
    }
}