{
    "Ar36": {
        "error": 0.0001739373619602313, 
        "filter_outliers_dict": {
            "filter_outliers": true, 
            "iterations": 1, 
            "std_devs": 10
        }, 
        "fit": "Parabolic", 
        "fn": 399, 
        "include_baseline_error": false, 
        "n": 400, 
        "value": 0.0034618962291398667
    }, 
    "Ar37": {
        "error": 0.004934929249598167, 
        "filter_outliers_dict": {
            "filter_outliers": true, 
            "iterations": 1, 
            "std_devs": 2
        }, 
        "fit": "Linear", 
        "fn": 385, 
        "include_baseline_error": false, 
        "n": 400, 
        "value": 0.042630660099537754
    }, 
    "Ar38": {
        "error": 0.002341976365630947, 
        "filter_outliers_dict": {
            "filter_outliers": true, 
            "iterations": 1, 
            "std_devs": 2
        }, 
        "fit": "Linear", 
        "fn": 384, 
        "include_baseline_error": false, 
        "n": 400, 
        "value": -0.01618989772923929
    }, 
    "Ar39": {
        "error": 0.009272248542116363, 
        "filter_outliers_dict": {
            "filter_outliers": true, 
            "iterations": 1, 
            "std_devs": 2
        }, 
        "fit": "Parabolic", 
        "fn": 381, 
        "include_baseline_error": false, 
        "n": 400, 
        "value": 0.17293287927854845
    }, 
    "Ar40": {
        "error": 0.006992126876459759, 
        "filter_outliers_dict": {
            "filter_outliers": true, 
            "iterations": 1, 
            "std_devs": 2
        }, 
        "fit": "Parabolic", 
        "fn": 383, 
        "include_baseline_error": false, 
        "n": 400, 
        "value": 0.39082404414991323
    }, 
    "Ar41": {
        "error": 0.001749008150074032, 
        "filter_outliers_dict": {
            "filter_outliers": true, 
            "iterations": 1, 
            "std_devs": 2
        }, 
        "fit": "Average", 
        "fn": 385, 
        "include_baseline_error": false, 
        "n": 400, 
        "value": -0.08049082817848432
    }, 
    "reviewed": true
}