{
    "AX": {
        "error": 0.00632835192907413, 
        "filter_outliers_dict": {
            "filter_outliers": true, 
            "iterations": 1, 
            "std_devs": 2
        }, 
        "fit": "average", 
        "value": 0.08508923799765167
    }, 
    "CDD": {
        "error": 2.1726403155052895e-05, 
        "filter_outliers_dict": {
            "filter_outliers": true, 
            "iterations": 1, 
            "std_devs": 10
        }, 
        "fit": "average", 
        "value": 0.00020273831254310126
    }, 
    "H1": {
        "error": 0.006592505329301432, 
        "filter_outliers_dict": {
            "filter_outliers": true, 
            "iterations": 1, 
            "std_devs": 2
        }, 
        "fit": "average", 
        "value": 0.11707986964709137
    }, 
    "H2": {
        "error": 0.0054668632469052104, 
        "filter_outliers_dict": {
            "filter_outliers": true, 
            "iterations": 1, 
            "std_devs": 2
        }, 
        "fit": "average", 
        "value": -0.10508066231369859
    }, 
    "L1": {
        "error": 0.002442343313413976, 
        "filter_outliers_dict": {
            "filter_outliers": true, 
            "iterations": 1, 
            "std_devs": 2
        }, 
        "fit": "average", 
        "value": -0.040093462111020675
    }, 
    "L2": {
        "error": 0.0051856477941783, 
        "filter_outliers_dict": {
            "filter_outliers": true, 
            "iterations": 1, 
            "std_devs": 2
        }, 
        "fit": "average", 
        "value": -0.000379938504266559
    }
}