{
    "Ar36": {
        "error": 0.0011475666891496374, 
        "filter_outliers_dict": {
            "filter_outliers": true, 
            "iterations": 1, 
            "std_devs": 2
        }, 
        "fit": "Linear", 
        "value": 0.2544843260492335
    }, 
    "Ar37": {
        "error": 0.010726953672574901, 
        "filter_outliers_dict": {
            "filter_outliers": true, 
            "iterations": 1, 
            "std_devs": 2
        }, 
        "fit": "linear", 
        "value": 0.033142220759840045
    }, 
    "Ar38": {
        "error": 0.005019360504474994, 
        "filter_outliers_dict": {
            "filter_outliers": true, 
            "iterations": 1, 
            "std_devs": 2
        }, 
        "fit": "linear", 
        "value": 1.1638386285183602
    }, 
    "Ar39": {
        "error": 0.025376869332969305, 
        "filter_outliers_dict": {
            "filter_outliers": true, 
            "iterations": 1, 
            "std_devs": 2
        }, 
        "fit": "Linear", 
        "value": 86.58382035737819
    }, 
    "Ar40": {
        "error": 0.06513256423784172, 
        "filter_outliers_dict": {
            "filter_outliers": true, 
            "iterations": 1, 
            "std_devs": 2
        }, 
        "fit": "Linear", 
        "value": 1143.9712284345987
    }, 
    "Ar41": {
        "error": 0.003216238881267796, 
        "filter_outliers_dict": {
            "filter_outliers": true, 
            "iterations": 1, 
            "std_devs": 2
        }, 
        "fit": "Average", 
        "value": -0.02707638802990014
    }
}