{
    "Ar36": {
        "error": 0.001126878780665546, 
        "filter_outliers_dict": {
            "filter_outliers": true, 
            "iterations": 1, 
            "std_devs": 2
        }, 
        "fit": "Linear", 
        "value": 0.25029960430522397
    }, 
    "Ar37": {
        "error": 0.009071953381852583, 
        "filter_outliers_dict": {
            "filter_outliers": true, 
            "iterations": 1, 
            "std_devs": 2
        }, 
        "fit": "linear", 
        "value": 0.07450450787388316
    }, 
    "Ar38": {
        "error": 0.005018761281219089, 
        "filter_outliers_dict": {
            "filter_outliers": true, 
            "iterations": 1, 
            "std_devs": 2
        }, 
        "fit": "linear", 
        "value": 1.1424069762552473
    }, 
    "Ar39": {
        "error": 0.021264243398625846, 
        "filter_outliers_dict": {
            "filter_outliers": true, 
            "iterations": 1, 
            "std_devs": 2
        }, 
        "fit": "Linear", 
        "value": 85.6165362184615
    }, 
    "Ar40": {
        "error": 0.056695739392191025, 
        "filter_outliers_dict": {
            "filter_outliers": true, 
            "iterations": 1, 
            "std_devs": 2
        }, 
        "fit": "Linear", 
        "value": 1131.1437982862171
    }, 
    "Ar41": {
        "error": 0.003217801096895672, 
        "filter_outliers_dict": {
            "filter_outliers": true, 
            "iterations": 1, 
            "std_devs": 2
        }, 
        "fit": "Average", 
        "value": -0.0336327913106319
    }
}