{
    "AX": {
        "error": 0.004739792929610511, 
        "filter_outliers_dict": {
            "filter_outliers": true, 
            "iterations": 1, 
            "std_devs": 2
        }, 
        "fit": "Average", 
        "fn": 115, 
        "include_baseline_error": false, 
        "n": 120, 
        "value": -0.05183621188170155
    }, 
    "CDD": {
        "error": 3.3921300853885733e-06, 
        "filter_outliers_dict": {
            "filter_outliers": true, 
            "iterations": 1, 
            "std_devs": 10
        }, 
        "fit": "Average", 
        "fn": 120, 
        "include_baseline_error": false, 
        "n": 120, 
        "value": 9.889673674479126e-06
    }, 
    "H1": {
        "error": 0.003954033650925509, 
        "filter_outliers_dict": {
            "filter_outliers": true, 
            "iterations": 1, 
            "std_devs": 2
        }, 
        "fit": "Average", 
        "fn": 115, 
        "include_baseline_error": false, 
        "n": 120, 
        "value": 0.06587889475808681
    }, 
    "H2": {
        "error": 0.0027862025199066713, 
        "filter_outliers_dict": {
            "filter_outliers": true, 
            "iterations": 1, 
            "std_devs": 2
        }, 
        "fit": "Average", 
        "fn": 114, 
        "include_baseline_error": false, 
        "n": 120, 
        "value": -0.09656500567992528
    }, 
    "L1": {
        "error": 0.0016765937081960613, 
        "filter_outliers_dict": {
            "filter_outliers": true, 
            "iterations": 1, 
            "std_devs": 2
        }, 
        "fit": "Average", 
        "fn": 114, 
        "include_baseline_error": false, 
        "n": 120, 
        "value": -0.02684780453401209
    }, 
    "L2": {
        "error": 0.004346288001904164, 
        "filter_outliers_dict": {
            "filter_outliers": true, 
            "iterations": 1, 
            "std_devs": 2
        }, 
        "fit": "Average", 
        "fn": 115, 
        "include_baseline_error": false, 
        "n": 120, 
        "value": -0.00920223122280415
    }
}